[{"model": "Llama-2-7b-chat-hf", "dataset": "squad", "metric": "rouge", "mode": "rougeL", "seed": 0, "temperature": 1.0, "ecc_u_agreement_erce": 0.31125294463778874, "degree_u_agreement_erce": 0.22562713457681544, "spectral_u_agreement_erce": 0.1825017265115021, "normalized_nll_all_erce": 0.03750035451250991, "unnormalized_nll_all_erce": 0.056875537838418255, "entropy_normalized_erce": 0.3062528973336516, "entropy_unnormalized_erce": 0.16750158459909043}, {"model": "Llama-2-7b-chat-hf", "dataset": "squad", "metric": "rouge", "mode": "rougeL", "seed": 1, "temperature": 1.0, "ecc_u_agreement_erce": 0.3262530865502004, "degree_u_agreement_erce": 0.13812630666490766, "spectral_u_agreement_erce": 0.1112510524722999, "normalized_nll_all_erce": 0.03562533684058829, "unnormalized_nll_all_erce": 0.06062557336127439, "entropy_normalized_erce": 0.3212530392460632, "entropy_unnormalized_erce": 0.20812696892282878}, {"model": "Llama-2-7b-chat-hf", "dataset": "squad", "metric": "rouge", "mode": "rougeL", "seed": 2, "temperature": 1.0, "ecc_u_agreement_erce": 0.31187795052842926, "degree_u_agreement_erce": 0.19125180933849545, "spectral_u_agreement_erce": 0.11750111155771825, "normalized_nll_all_erce": 0.04625043733950324, "unnormalized_nll_all_erce": 0.05562552605713718, "entropy_normalized_erce": 0.29125275542123985, "entropy_unnormalized_erce": 0.1675015845990905}, {"model": "Llama-2-7b-chat-hf", "dataset": "squad", "metric": "rouge", "mode": "rougeL", "seed": 3, "temperature": 1.0, "ecc_u_agreement_erce": 0.2868777140077432, "degree_u_agreement_erce": 0.20187690983741047, "spectral_u_agreement_erce": 0.14687638949190104, "normalized_nll_all_erce": 0.03750035451250992, "unnormalized_nll_all_erce": 0.0643756088841305, "entropy_normalized_erce": 0.3062528973336516, "entropy_unnormalized_erce": 0.18687676792499874}, {"model": "Llama-2-7b-chat-hf", "dataset": "squad", "metric": "rouge", "mode": "rougeL", "seed": 4, "temperature": 1.0, "ecc_u_agreement_erce": 0.2768776193994688, "degree_u_agreement_erce": 0.14625138360126044, "spectral_u_agreement_erce": 0.11625109977643712, "normalized_nll_all_erce": 0.04562543144886271, "unnormalized_nll_all_erce": 0.06375060299348993, "entropy_normalized_erce": 0.33125313385433763, "entropy_unnormalized_erce": 0.18375173829278324}, {"model": "Llama-2-7b-chat-hf", "dataset": "squad", "metric": "rouge", "mode": "rougeL", "seed": 5, "temperature": 1.0, "ecc_u_agreement_erce": 0.3068779032242921, "degree_u_agreement_erce": 0.2331272054435149, "spectral_u_agreement_erce": 0.1431263539690449, "normalized_nll_all_erce": 0.023750224381379362, "unnormalized_nll_all_erce": 0.05562552605713717, "entropy_normalized_erce": 0.2912527554212398, "entropy_unnormalized_erce": 0.12812621205663324}, {"model": "Llama-2-7b-chat-hf", "dataset": "squad", "metric": "rouge", "mode": "rougeL", "seed": 6, "temperature": 1.0, "ecc_u_agreement_erce": 0.22250210494459988, "degree_u_agreement_erce": 0.1556264723188944, "spectral_u_agreement_erce": 0.12062614118993378, "normalized_nll_all_erce": 0.042500401816647146, "unnormalized_nll_all_erce": 0.05187549053428103, "entropy_normalized_erce": 0.3012528500295143, "entropy_unnormalized_erce": 0.1525014426866788}, {"model": "Llama-2-7b-chat-hf", "dataset": "squad", "metric": "rouge", "mode": "rougeL", "seed": 7, "temperature": 1.0, "ecc_u_agreement_erce": 0.2612524715964165, "degree_u_agreement_erce": 0.15687648410017546, "spectral_u_agreement_erce": 0.09437589270895384, "normalized_nll_all_erce": 0.04125039003536602, "unnormalized_nll_all_erce": 0.060625573361274346, "entropy_normalized_erce": 0.32062803335542256, "entropy_unnormalized_erce": 0.18875178559692044}, {"model": "Llama-2-7b-chat-hf", "dataset": "squad", "metric": "rouge", "mode": "rougeL", "seed": 8, "temperature": 1.0, "ecc_u_agreement_erce": 0.30687790322429204, "degree_u_agreement_erce": 0.1625015372949532, "spectral_u_agreement_erce": 0.1762516674260838, "normalized_nll_all_erce": 0.03375031898965379, "unnormalized_nll_all_erce": 0.05250049642492161, "entropy_normalized_erce": 0.2962528027253771, "entropy_unnormalized_erce": 0.20125190394676992}, {"model": "Llama-2-7b-chat-hf", "dataset": "squad", "metric": "rouge", "mode": "rougeL", "seed": 9, "temperature": 1.0, "ecc_u_agreement_erce": 0.23125218777159318, "degree_u_agreement_erce": 0.17625166742608384, "spectral_u_agreement_erce": 0.15625147820953497, "normalized_nll_all_erce": 0.03687534862186937, "unnormalized_nll_all_erce": 0.04250040181664715, "entropy_normalized_erce": 0.3118779505284293, "entropy_unnormalized_erce": 0.18875178559692044}, {"model": "Llama-2-7b-chat-hf", "dataset": "squad", "metric": "rouge", "mode": "rougeL", "seed": 10, "temperature": 1.0, "ecc_u_agreement_erce": 0.2568774301829199, "degree_u_agreement_erce": 0.19125180933849548, "spectral_u_agreement_erce": 0.18750177381563932, "normalized_nll_all_erce": 0.02500023616266045, "unnormalized_nll_all_erce": 0.0606255733612744, "entropy_normalized_erce": 0.3262530865502004, "entropy_unnormalized_erce": 0.19250182111977654}, {"model": "Llama-2-7b-chat-hf", "dataset": "squad", "metric": "rouge", "mode": "rougeL", "seed": 11, "temperature": 1.0, "ecc_u_agreement_erce": 0.2862527081171027, "degree_u_agreement_erce": 0.14187634218776385, "spectral_u_agreement_erce": 0.17187662601258713, "normalized_nll_all_erce": 0.03625034273122881, "unnormalized_nll_all_erce": 0.04375041359792823, "entropy_normalized_erce": 0.3012528500295143, "entropy_unnormalized_erce": 0.16812659048973097}, {"model": "Llama-2-7b-chat-hf", "dataset": "squad", "metric": "rouge", "mode": "rougeL", "seed": 12, "temperature": 1.0, "ecc_u_agreement_erce": 0.2425022941611487, "degree_u_agreement_erce": 0.17750167920736487, "spectral_u_agreement_erce": 0.13187624757948938, "normalized_nll_all_erce": 0.02750025990423548, "unnormalized_nll_all_erce": 0.055625526057137144, "entropy_normalized_erce": 0.32625308655020036, "entropy_unnormalized_erce": 0.17187662601258713}, {"model": "Llama-2-7b-chat-hf", "dataset": "squad", "metric": "rouge", "mode": "rougeL", "seed": 13, "temperature": 1.0, "ecc_u_agreement_erce": 0.24562732379336438, "degree_u_agreement_erce": 0.19125180933849542, "spectral_u_agreement_erce": 0.12187615297121493, "normalized_nll_all_erce": 0.028125265794876026, "unnormalized_nll_all_erce": 0.060625573361274374, "entropy_normalized_erce": 0.316252991941926, "entropy_unnormalized_erce": 0.17687667331672433}, {"model": "Llama-2-7b-chat-hf", "dataset": "squad", "metric": "rouge", "mode": "rougeL", "seed": 14, "temperature": 1.0, "ecc_u_agreement_erce": 0.25687743018291986, "degree_u_agreement_erce": 0.18187672062086152, "spectral_u_agreement_erce": 0.15250144268667884, "normalized_nll_all_erce": 0.023750224381379356, "unnormalized_nll_all_erce": 0.05062547875299992, "entropy_normalized_erce": 0.32125303924606313, "entropy_unnormalized_erce": 0.1481264012731821}, {"model": "Llama-2-7b-chat-hf", "dataset": "squad", "metric": "rouge", "mode": "rougeL", "seed": 15, "temperature": 1.0, "ecc_u_agreement_erce": 0.215627039968541, "degree_u_agreement_erce": 0.12312616475249603, "spectral_u_agreement_erce": 0.09375088681831331, "normalized_nll_all_erce": 0.03250030720837271, "unnormalized_nll_all_erce": 0.043125407707287684, "entropy_normalized_erce": 0.31125294463778874, "entropy_unnormalized_erce": 0.14750139538254156}, {"model": "Llama-2-7b-chat-hf", "dataset": "squad", "metric": "rouge", "mode": "rougeL", "seed": 16, "temperature": 1.0, "ecc_u_agreement_erce": 0.3168779978325665, "degree_u_agreement_erce": 0.1818767206208615, "spectral_u_agreement_erce": 0.16125152551367217, "normalized_nll_all_erce": 0.0325003072083727, "unnormalized_nll_all_erce": 0.05312550231556214, "entropy_normalized_erce": 0.3362531811584748, "entropy_unnormalized_erce": 0.258127441964201}, {"model": "Llama-2-7b-chat-hf", "dataset": "squad", "metric": "rouge", "mode": "rougeL", "seed": 17, "temperature": 1.0, "ecc_u_agreement_erce": 0.31062793874714817, "degree_u_agreement_erce": 0.11312607014422157, "spectral_u_agreement_erce": 0.17187662601258713, "normalized_nll_all_erce": 0.03687534862186936, "unnormalized_nll_all_erce": 0.05125048464364049, "entropy_normalized_erce": 0.31562798605128534, "entropy_unnormalized_erce": 0.2418772882705082}, {"model": "Llama-2-7b-chat-hf", "dataset": "squad", "metric": "rouge", "mode": "rougeL", "seed": 18, "temperature": 1.0, "ecc_u_agreement_erce": 0.21875206942174377, "degree_u_agreement_erce": 0.11750111155771825, "spectral_u_agreement_erce": 0.1012509578640255, "normalized_nll_all_erce": 0.04125039003536604, "unnormalized_nll_all_erce": 0.06375060299348996, "entropy_normalized_erce": 0.3062528973336515, "entropy_unnormalized_erce": 0.2312521877715932}, {"model": "Llama-2-7b-chat-hf", "dataset": "squad", "metric": "rouge", "mode": "rougeL", "seed": 19, "temperature": 1.0, "ecc_u_agreement_erce": 0.37625355959157264, "degree_u_agreement_erce": 0.16750158459909043, "spectral_u_agreement_erce": 0.12625119438471158, "normalized_nll_all_erce": 0.02437523027201993, "unnormalized_nll_all_erce": 0.0656256206654116, "entropy_normalized_erce": 0.2962528027253771, "entropy_unnormalized_erce": 0.189376791487561}]