[{"model": "Llama-2-7b-chat-hf", "dataset": "nq-open", "metric": "bert_similarity", "mode": "rougeL", "seed": 0, "temperature": 0.6, "ecc_u_disagreement_erce": 0.3203103352729288, "degree_u_disagreement_erce": 0.35140964148569787, "spectral_u_disagreement_erce": 0.3457105159538827, "ecc_u_agreement_erce": 0.29524772249124803, "degree_u_agreement_erce": 0.3257810383244719, "spectral_u_agreement_erce": 0.27196735769072244, "normalized_nll_greedy_erce": 0.37138079700717425, "unnormalized_nll_greedy_erce": 0.34995828373050136, "entropy_normalized_erce": 0.3252008482947755, "entropy_unnormalized_erce": 0.30013823551309476, "ecc_c_disagreement_erce": 0.2856329120771986, "degree_c_disagreement_erce": 0.3118836388604775, "ecc_c_agreement_erce": 0.296258206214842, "degree_c_agreement_erce": 0.35000969555943373, "normalized_nll_all_erce": 0.46501288124324774, "unnormalized_nll_all_erce": 0.4300119116873043}, {"model": "Llama-2-7b-chat-hf", "dataset": "nq-open", "metric": "bert_similarity", "mode": "rougeL", "seed": 1, "temperature": 0.6, "ecc_u_disagreement_erce": 0.3549597842881255, "degree_u_disagreement_erce": 0.3658405540473225, "spectral_u_disagreement_erce": 0.3400386383993847, "ecc_u_agreement_erce": 0.38702842769960294, "degree_u_agreement_erce": 0.3224995375519343, "spectral_u_agreement_erce": 0.34146919558598116, "normalized_nll_greedy_erce": 0.2864403319187412, "unnormalized_nll_greedy_erce": 0.3257947774454292, "entropy_normalized_erce": 0.39075057815602565, "entropy_unnormalized_erce": 0.42572569806631466, "ecc_c_disagreement_erce": 0.36501011108340947, "degree_c_disagreement_erce": 0.41501149616332855, "ecc_c_agreement_erce": 0.33250921001410483, "degree_c_agreement_erce": 0.35563485118908533, "normalized_nll_all_erce": 0.2850078949555389, "unnormalized_nll_all_erce": 0.2506319425212552}, {"model": "Llama-2-7b-chat-hf", "dataset": "nq-open", "metric": "bert_similarity", "mode": "rougeL", "seed": 2, "temperature": 0.6, "ecc_u_disagreement_erce": 0.37094567367361836, "degree_u_disagreement_erce": 0.4056371076003435, "spectral_u_disagreement_erce": 0.3713249962198229, "ecc_u_agreement_erce": 0.39130305967921064, "degree_u_agreement_erce": 0.4003601338297838, "spectral_u_agreement_erce": 0.40508454932229293, "normalized_nll_greedy_erce": 0.37021343225500425, "unnormalized_nll_greedy_erce": 0.400166251039069, "entropy_normalized_erce": 0.40566458584225795, "entropy_unnormalized_erce": 0.4563485100729249, "ecc_c_disagreement_erce": 0.3962609763746803, "degree_c_disagreement_erce": 0.3850106651153771, "ecc_c_agreement_erce": 0.3762604223427126, "degree_c_agreement_erce": 0.3800105266073852, "normalized_nll_all_erce": 0.28688294632051786, "unnormalized_nll_all_erce": 0.3200088645114822}, {"model": "Llama-2-7b-chat-hf", "dataset": "nq-open", "metric": "bert_similarity", "mode": "rougeL", "seed": 3, "temperature": 0.6, "ecc_u_disagreement_erce": 0.2900802779140176, "degree_u_disagreement_erce": 0.3352314811616695, "spectral_u_disagreement_erce": 0.292084117192399, "ecc_u_agreement_erce": 0.31588917825473256, "degree_u_agreement_erce": 0.37578107670190486, "spectral_u_agreement_erce": 0.37089056368005807, "normalized_nll_greedy_erce": 0.3457240248102428, "unnormalized_nll_greedy_erce": 0.350877960531113, "entropy_normalized_erce": 0.2963249002762407, "entropy_unnormalized_erce": 0.29636074479851465, "ecc_c_disagreement_erce": 0.3356342971571177, "degree_c_disagreement_erce": 0.30500844898750656, "ecc_c_agreement_erce": 0.3950109421313609, "degree_c_agreement_erce": 0.3750103880993933, "normalized_nll_all_erce": 0.4350120501952962, "unnormalized_nll_all_erce": 0.46501288124324774}, {"model": "Llama-2-7b-chat-hf", "dataset": "nq-open", "metric": "bert_similarity", "mode": "rougeL", "seed": 4, "temperature": 0.6, "ecc_u_disagreement_erce": 0.2020800568600045, "degree_u_disagreement_erce": 0.22591942734729809, "spectral_u_disagreement_erce": 0.2699361169252922, "ecc_u_agreement_erce": 0.31640688982376314, "degree_u_agreement_erce": 0.2750206662475851, "spectral_u_agreement_erce": 0.2706342791835431, "normalized_nll_greedy_erce": 0.3356104966884113, "unnormalized_nll_greedy_erce": 0.3499860689918787, "entropy_normalized_erce": 0.2212003846953868, "entropy_unnormalized_erce": 0.3255731093933372, "ecc_c_disagreement_erce": 0.20563069594932798, "degree_c_disagreement_erce": 0.19625543605500384, "ecc_c_agreement_erce": 0.25688211527256644, "degree_c_agreement_erce": 0.225006232859636, "normalized_nll_all_erce": 0.226881284224615, "unnormalized_nll_all_erce": 0.21063083445731995}, {"model": "Llama-2-7b-chat-hf", "dataset": "nq-open", "metric": "bert_similarity", "mode": "rougeL", "seed": 5, "temperature": 0.6, "ecc_u_disagreement_erce": 0.36140558115330323, "degree_u_disagreement_erce": 0.38068548235444016, "spectral_u_disagreement_erce": 0.3751039452768509, "ecc_u_agreement_erce": 0.4253116055659559, "degree_u_agreement_erce": 0.2856316426539069, "spectral_u_agreement_erce": 0.33188734841873463, "normalized_nll_greedy_erce": 0.29505399321026465, "unnormalized_nll_greedy_erce": 0.2513264392112977, "entropy_normalized_erce": 0.3556647009745565, "entropy_unnormalized_erce": 0.3550148942816857, "ecc_c_disagreement_erce": 0.40563623626900447, "degree_c_disagreement_erce": 0.40063609776101256, "ecc_c_agreement_erce": 0.26063221953723903, "degree_c_agreement_erce": 0.30188336184449366, "normalized_nll_all_erce": 0.28625792919885823, "unnormalized_nll_all_erce": 0.26563235804523094}, {"model": "Llama-2-7b-chat-hf", "dataset": "nq-open", "metric": "bert_similarity", "mode": "rougeL", "seed": 6, "temperature": 0.6, "ecc_u_disagreement_erce": 0.34984760321418673, "degree_u_disagreement_erce": 0.36655245542653064, "spectral_u_disagreement_erce": 0.3551814523402175, "ecc_u_agreement_erce": 0.4307616615586303, "degree_u_agreement_erce": 0.3356315275216084, "spectral_u_agreement_erce": 0.3212902646431014, "normalized_nll_greedy_erce": 0.42053729941075285, "unnormalized_nll_greedy_erce": 0.38505106884988205, "entropy_normalized_erce": 0.35098019801220254, "entropy_unnormalized_erce": 0.3250068119943293, "ecc_c_disagreement_erce": 0.37063526671306113, "degree_c_disagreement_erce": 0.36563512820506916, "ecc_c_agreement_erce": 0.3256340201411339, "degree_c_agreement_erce": 0.30563346610916614, "normalized_nll_all_erce": 0.4150114961633285, "unnormalized_nll_all_erce": 0.4000110806393528}, {"model": "Llama-2-7b-chat-hf", "dataset": "nq-open", "metric": "bert_similarity", "mode": "rougeL", "seed": 7, "temperature": 0.6, "ecc_u_disagreement_erce": 0.24601346740873276, "degree_u_disagreement_erce": 0.27530312415329783, "spectral_u_disagreement_erce": 0.290320981172799, "ecc_u_agreement_erce": 0.34528928525101527, "degree_u_agreement_erce": 0.26546668109658145, "spectral_u_agreement_erce": 0.3050014238027584, "normalized_nll_greedy_erce": 0.32631256576932555, "unnormalized_nll_greedy_erce": 0.32064122549888735, "entropy_normalized_erce": 0.3008987227222802, "entropy_unnormalized_erce": 0.320675688433579, "ecc_c_disagreement_erce": 0.28063277356920663, "degree_c_disagreement_erce": 0.3400094185434499, "ecc_c_agreement_erce": 0.3650101110834094, "degree_c_agreement_erce": 0.3262590372627935, "normalized_nll_all_erce": 0.32500900301947416, "unnormalized_nll_all_erce": 0.28125779069086637}, {"model": "Llama-2-7b-chat-hf", "dataset": "nq-open", "metric": "bert_similarity", "mode": "rougeL", "seed": 8, "temperature": 0.6, "ecc_u_disagreement_erce": 0.36023836991086455, "degree_u_disagreement_erce": 0.37546392559690345, "spectral_u_disagreement_erce": 0.37037937627461043, "ecc_u_agreement_erce": 0.3857976634283789, "degree_u_agreement_erce": 0.3507048783089982, "spectral_u_agreement_erce": 0.3309348972904765, "normalized_nll_greedy_erce": 0.3801051388150123, "unnormalized_nll_greedy_erce": 0.321650705492348, "entropy_normalized_erce": 0.35668124241565985, "entropy_unnormalized_erce": 0.27256159386083884, "ecc_c_disagreement_erce": 0.3662601453267288, "degree_c_disagreement_erce": 0.3850106651153771, "ecc_c_agreement_erce": 0.3106336046171581, "degree_c_agreement_erce": 0.33500928003545805, "normalized_nll_all_erce": 0.27625765218287446, "unnormalized_nll_all_erce": 0.2562570981509068}, {"model": "Llama-2-7b-chat-hf", "dataset": "nq-open", "metric": "bert_similarity", "mode": "rougeL", "seed": 9, "temperature": 0.6, "ecc_u_disagreement_erce": 0.40542211722156596, "degree_u_disagreement_erce": 0.4106665469290762, "spectral_u_disagreement_erce": 0.3917103977513895, "ecc_u_agreement_erce": 0.4209046481979108, "degree_u_agreement_erce": 0.38996952064283724, "spectral_u_agreement_erce": 0.3906259282541569, "normalized_nll_greedy_erce": 0.3114747756647163, "unnormalized_nll_greedy_erce": 0.3302574588459599, "entropy_normalized_erce": 0.4351205703807579, "entropy_unnormalized_erce": 0.3960498108376336, "ecc_c_disagreement_erce": 0.4600127427352558, "degree_c_disagreement_erce": 0.500013850799191, "ecc_c_agreement_erce": 0.46063775985691546, "degree_c_agreement_erce": 0.38001052660738527, "normalized_nll_all_erce": 0.35563485118908533, "unnormalized_nll_all_erce": 0.35188474692441274}, {"model": "Llama-2-7b-chat-hf", "dataset": "nq-open", "metric": "bert_similarity", "mode": "rougeL", "seed": 10, "temperature": 0.6, "ecc_u_disagreement_erce": 0.3455857125422823, "degree_u_disagreement_erce": 0.3106660096450164, "spectral_u_disagreement_erce": 0.3105967000013048, "ecc_u_agreement_erce": 0.39081290310696015, "degree_u_agreement_erce": 0.3599889165973954, "spectral_u_agreement_erce": 0.3499306519788556, "normalized_nll_greedy_erce": 0.26063803249647505, "unnormalized_nll_greedy_erce": 0.3300637295649764, "entropy_normalized_erce": 0.26385774560213815, "entropy_unnormalized_erce": 0.2907021458357799, "ecc_c_disagreement_erce": 0.3356342971571176, "degree_c_disagreement_erce": 0.39001080362336904, "ecc_c_agreement_erce": 0.32500900301947416, "degree_c_agreement_erce": 0.3456345741731015, "normalized_nll_all_erce": 0.25250699388623415, "unnormalized_nll_all_erce": 0.31563374312515}, {"model": "Llama-2-7b-chat-hf", "dataset": "nq-open", "metric": "bert_similarity", "mode": "rougeL", "seed": 11, "temperature": 0.6, "ecc_u_disagreement_erce": 0.2918484029998872, "degree_u_disagreement_erce": 0.3053059871097878, "spectral_u_disagreement_erce": 0.29593890005672174, "ecc_u_agreement_erce": 0.3259264887949409, "degree_u_agreement_erce": 0.25697766970692687, "spectral_u_agreement_erce": 0.2613431026926375, "normalized_nll_greedy_erce": 0.27122805482446544, "unnormalized_nll_greedy_erce": 0.2662403701426643, "entropy_normalized_erce": 0.2956826155602069, "entropy_unnormalized_erce": 0.33003594430359917, "ecc_c_disagreement_erce": 0.3250090030194742, "degree_c_disagreement_erce": 0.2762576521828744, "ecc_c_agreement_erce": 0.31563374312515, "degree_c_agreement_erce": 0.3506347126810934, "normalized_nll_all_erce": 0.2706324965532228, "unnormalized_nll_all_erce": 0.27500761793955514}, {"model": "Llama-2-7b-chat-hf", "dataset": "nq-open", "metric": "bert_similarity", "mode": "rougeL", "seed": 12, "temperature": 0.6, "ecc_u_disagreement_erce": 0.29089434001944975, "degree_u_disagreement_erce": 0.32511764602037535, "spectral_u_disagreement_erce": 0.32570466723311753, "ecc_u_agreement_erce": 0.39579367985085, "degree_u_agreement_erce": 0.34590931105600115, "spectral_u_agreement_erce": 0.3403762062986578, "normalized_nll_greedy_erce": 0.38576273996449323, "unnormalized_nll_greedy_erce": 0.2713321344223313, "entropy_normalized_erce": 0.33498202784820036, "entropy_unnormalized_erce": 0.28588746662122777, "ecc_c_disagreement_erce": 0.4100113576553367, "degree_c_disagreement_erce": 0.34000941854344996, "ecc_c_agreement_erce": 0.3456345741731015, "degree_c_agreement_erce": 0.3650101110834096, "normalized_nll_all_erce": 0.3656351282050691, "unnormalized_nll_all_erce": 0.27000747943156317}, {"model": "Llama-2-7b-chat-hf", "dataset": "nq-open", "metric": "bert_similarity", "mode": "rougeL", "seed": 13, "temperature": 0.6, "ecc_u_disagreement_erce": 0.4000828952549374, "degree_u_disagreement_erce": 0.36577807558665665, "spectral_u_disagreement_erce": 0.36695242503160386, "ecc_u_agreement_erce": 0.39584894335414156, "degree_u_agreement_erce": 0.34604109916037845, "spectral_u_agreement_erce": 0.3163791813172516, "normalized_nll_greedy_erce": 0.3519350285412969, "unnormalized_nll_greedy_erce": 0.3563560320497617, "entropy_normalized_erce": 0.3455028172873449, "entropy_unnormalized_erce": 0.400277085065115, "ecc_c_disagreement_erce": 0.4200116346713205, "degree_c_disagreement_erce": 0.37688543946437225, "ecc_c_agreement_erce": 0.3300091415274661, "degree_c_agreement_erce": 0.3356342971571177, "normalized_nll_all_erce": 0.34000941854345, "unnormalized_nll_all_erce": 0.38563568223703676}, {"model": "Llama-2-7b-chat-hf", "dataset": "nq-open", "metric": "bert_similarity", "mode": "rougeL", "seed": 14, "temperature": 0.6, "ecc_u_disagreement_erce": 0.3751592087801426, "degree_u_disagreement_erce": 0.38563824357235565, "spectral_u_disagreement_erce": 0.3798559925210058, "ecc_u_agreement_erce": 0.4202826267664173, "degree_u_agreement_erce": 0.350235215285885, "spectral_u_agreement_erce": 0.33017441008129106, "normalized_nll_greedy_erce": 0.38571446115397867, "unnormalized_nll_greedy_erce": 0.28815979441976786, "entropy_normalized_erce": 0.4250899375138639, "entropy_unnormalized_erce": 0.4017751865335123, "ecc_c_disagreement_erce": 0.3800105266073852, "degree_c_disagreement_erce": 0.37001024959140144, "ecc_c_agreement_erce": 0.36000997257541767, "degree_c_agreement_erce": 0.31563374312515, "normalized_nll_all_erce": 0.39063582074502873, "unnormalized_nll_all_erce": 0.36063498969707725}, {"model": "Llama-2-7b-chat-hf", "dataset": "nq-open", "metric": "bert_similarity", "mode": "rougeL", "seed": 15, "temperature": 0.6, "ecc_u_disagreement_erce": 0.3650178953969339, "degree_u_disagreement_erce": 0.3949708676907301, "spectral_u_disagreement_erce": 0.37021327874527293, "ecc_u_agreement_erce": 0.3808517333935092, "degree_u_agreement_erce": 0.3701300764708727, "spectral_u_agreement_erce": 0.3562795074486759, "normalized_nll_greedy_erce": 0.3706618341803233, "unnormalized_nll_greedy_erce": 0.3152259394603672, "entropy_normalized_erce": 0.3656188859952304, "entropy_unnormalized_erce": 0.31083924537686247, "ecc_c_disagreement_erce": 0.4106363747769964, "degree_c_disagreement_erce": 0.39001080362336904, "ecc_c_agreement_erce": 0.43001191168730435, "degree_c_agreement_erce": 0.36000997257541756, "normalized_nll_all_erce": 0.3406344356651096, "unnormalized_nll_all_erce": 0.2562570981509068}, {"model": "Llama-2-7b-chat-hf", "dataset": "nq-open", "metric": "bert_similarity", "mode": "rougeL", "seed": 16, "temperature": 0.6, "ecc_u_disagreement_erce": 0.21014085285401454, "degree_u_disagreement_erce": 0.23612851527690473, "spectral_u_disagreement_erce": 0.23023005735891108, "ecc_u_agreement_erce": 0.3611301079403676, "degree_u_agreement_erce": 0.2600167786136383, "spectral_u_agreement_erce": 0.3156327402484862, "normalized_nll_greedy_erce": 0.3059352234986556, "unnormalized_nll_greedy_erce": 0.3404181144553206, "entropy_normalized_erce": 0.29128947406798483, "entropy_unnormalized_erce": 0.3048629580250666, "ecc_c_disagreement_erce": 0.26063221953723903, "degree_c_disagreement_erce": 0.24563180401326332, "ecc_c_agreement_erce": 0.17250477775836368, "degree_c_agreement_erce": 0.28063277356920674, "normalized_nll_all_erce": 0.35063471268109336, "unnormalized_nll_all_erce": 0.30625848323082583}, {"model": "Llama-2-7b-chat-hf", "dataset": "nq-open", "metric": "bert_similarity", "mode": "rougeL", "seed": 17, "temperature": 0.6, "ecc_u_disagreement_erce": 0.3501246882793017, "degree_u_disagreement_erce": 0.3858393413204447, "spectral_u_disagreement_erce": 0.3857698781670017, "ecc_u_agreement_erce": 0.4401219174286506, "degree_u_agreement_erce": 0.39085442748929466, "spectral_u_agreement_erce": 0.42574634512518333, "normalized_nll_greedy_erce": 0.34631833773522486, "unnormalized_nll_greedy_erce": 0.3020669317779727, "entropy_normalized_erce": 0.4003601338297838, "entropy_unnormalized_erce": 0.3802159728410583, "ecc_c_disagreement_erce": 0.34563457417310145, "degree_c_disagreement_erce": 0.3656351282050691, "ecc_c_agreement_erce": 0.4106363747769963, "degree_c_agreement_erce": 0.45001246571927195, "normalized_nll_all_erce": 0.32125889875480157, "unnormalized_nll_all_erce": 0.36501011108340947}, {"model": "Llama-2-7b-chat-hf", "dataset": "nq-open", "metric": "bert_similarity", "mode": "rougeL", "seed": 18, "temperature": 0.6, "ecc_u_disagreement_erce": 0.29027431421446387, "degree_u_disagreement_erce": 0.2162752552291171, "spectral_u_disagreement_erce": 0.2499582069756357, "ecc_u_agreement_erce": 0.2848296310623871, "degree_u_agreement_erce": 0.24082652709561894, "spectral_u_agreement_erce": 0.2500137774983901, "normalized_nll_greedy_erce": 0.3100304026022969, "unnormalized_nll_greedy_erce": 0.2751870707963855, "entropy_normalized_erce": 0.26070081797660355, "entropy_unnormalized_erce": 0.27136682762162007, "ecc_c_disagreement_erce": 0.23125640561094718, "degree_c_disagreement_erce": 0.2162559900869715, "ecc_c_agreement_erce": 0.18813021040399905, "degree_c_agreement_erce": 0.27125751367488254, "normalized_nll_all_erce": 0.3650101110834095, "unnormalized_nll_all_erce": 0.32125889875480157}, {"model": "Llama-2-7b-chat-hf", "dataset": "nq-open", "metric": "bert_similarity", "mode": "rougeL", "seed": 19, "temperature": 0.6, "ecc_u_disagreement_erce": 0.2965052742105954, "degree_u_disagreement_erce": 0.3057892357441269, "spectral_u_disagreement_erce": 0.30639022634242347, "ecc_u_agreement_erce": 0.33581151768163464, "degree_u_agreement_erce": 0.2766920034478286, "spectral_u_agreement_erce": 0.31989447741065924, "normalized_nll_greedy_erce": 0.41065894819737353, "unnormalized_nll_greedy_erce": 0.37004702770620385, "entropy_normalized_erce": 0.37082823872912357, "entropy_unnormalized_erce": 0.3907089770188257, "ecc_c_disagreement_erce": 0.3250090030194742, "degree_c_disagreement_erce": 0.320633881633142, "ecc_c_agreement_erce": 0.2662573751668906, "degree_c_agreement_erce": 0.28625792919885823, "normalized_nll_all_erce": 0.47001301975123966, "unnormalized_nll_all_erce": 0.4462623614545994}]